{
  "abstract": "Typological features of lama1292. Coded by Hanna Fricke following ['/vol/winshare/Public/ResearchData/HUM/LUCL-KlamerVICI/Lesser Sunda Database/HWA_HF_2014_typological questionnaire Hewa.xlsx', 'Fricke 2014'].",
  "comment": "",
  "created": [
    "December 2014"
  ],
  "creator": [
    "Hanna Fricke"
  ],
  "id": "lama1292",
  "language": "lama1292",
  "name": "HWA_HF_2014_typological questionnaire Hewa.xlsx",
  "references": [
    "Fricke 2014"
  ],
  "source": [
    "/vol/winshare/Public/ResearchData/HUM/LUCL-KlamerVICI/Lesser Sunda Database/HWA_HF_2014_typological questionnaire Hewa.xlsx"
  ]
}